soon/__init__.py
soon/__main__.py
soon_bin-0.1.6.data/scripts/soon
soon_bin-0.1.6.dist-info/METADATA
soon_bin-0.1.6.dist-info/WHEEL
soon_bin-0.1.6.dist-info/licenses/LICENSE
soon_bin-0.1.6.dist-info/RECORD
