Metadata-Version: 2.4
Name: soon-bin
Version: 0.1.6
Classifier: Programming Language :: Rust
Classifier: Programming Language :: Python :: Implementation :: CPython
Classifier: Programming Language :: Python :: Implementation :: PyPy
Requires-Dist: rich>=14.0.0
License-File: LICENSE
Summary: Predict your next shell command based on history — like shell autocomplete, but MORE stupid
Author: HsiangNianian
Author-email: HsiangNianian <i@jyunko.cn>
License: MIT
Requires-Python: >=3.10
Project-URL: Source Code, https://github.com/HsiangNianian/soon
